MANIFEST.in
README.md
setup.py
sf/__init__.py
sf/api.py
sf/comm/__init__.py
sf/comm/comm.py
sf/comm/exceptions.py
sf/comm/token.py
sf/data/express_type.csv
sf/model/__init__.py
sf/model/address.py
sf/model/cargo.py
sf/model/contact.py
sf/model/service.py
sf/order/__init__.py
sf/order/order.py
sf/order/sheet.py
sf_sdk.egg-info/PKG-INFO
sf_sdk.egg-info/SOURCES.txt
sf_sdk.egg-info/dependency_links.txt
sf_sdk.egg-info/requires.txt
sf_sdk.egg-info/top_level.txt
sf_sdk.egg-info/zip-safe
tests/__init__.py
tests/test_order.py